pydcop/__init__.py
pydcop/dcop.py
pydcop/algorithms/__init__.py
pydcop/algorithms/dba.py
pydcop/algorithms/dpop.py
pydcop/algorithms/dsa.py
pydcop/algorithms/gdba.py
pydcop/algorithms/generic_computations.py
pydcop/algorithms/graphs.py
pydcop/algorithms/maxsum.py
pydcop/algorithms/maxsum_dynamic.py
pydcop/algorithms/mgm.py
pydcop/algorithms/mgm2.py
pydcop/algorithms/mixeddsa.py
pydcop/algorithms/objects.py
pydcop/commands/__init__.py
pydcop/commands/_utils.py
pydcop/commands/agent.py
pydcop/commands/distribute.py
pydcop/commands/generate.py
pydcop/commands/graph.py
pydcop/commands/orchestrator.py
pydcop/commands/replica_dist.py
pydcop/commands/run.py
pydcop/commands/solve.py
pydcop/commands/generators/__init__.py
pydcop/commands/generators/iot.py
pydcop/commands/generators/smallworld.py
pydcop/computations_graph/__init__.py
pydcop/computations_graph/constraints_hypergraph.py
pydcop/computations_graph/factor_graph.py
pydcop/computations_graph/objects.py
pydcop/computations_graph/pseudotree.py
pydcop/dcop/__init__.py
pydcop/dcop/dcop.py
pydcop/dcop/objects.py
pydcop/dcop/relations.py
pydcop/dcop/scenario.py
pydcop/dcop/yamldcop.py
pydcop/distribution/__init__.py
pydcop/distribution/adhoc.py
pydcop/distribution/heur_comhost.py
pydcop/distribution/ilp_compref.py
pydcop/distribution/ilp_fgdp.py
pydcop/distribution/objects.py
pydcop/distribution/oneagent.py
pydcop/distribution/yamlformat.py
pydcop/infrastructure/__init__.py
pydcop/infrastructure/agents.py
pydcop/infrastructure/communication.py
pydcop/infrastructure/computations.py
pydcop/infrastructure/discovery.py
pydcop/infrastructure/orchestratedagents.py
pydcop/infrastructure/orchestrator.py
pydcop/infrastructure/run.py
pydcop/infrastructure/stats.py
pydcop/infrastructure/ui.py
pydcop/reparation/__init__.py
pydcop/reparation/removal.py
pydcop/replication/__init__.py
pydcop/replication/dist_ucs_hostingcosts.py
pydcop/replication/objects.py
pydcop-0.1.1.dist-info/LICENSE.txt
pydcop-0.1.1.dist-info/METADATA
pydcop-0.1.1.dist-info/RECORD
pydcop-0.1.1.dist-info/WHEEL
pydcop-0.1.1.dist-info/top_level.txt
