Metadata-Version: 2.1
Name: pydcop
Version: 0.1.1
Summary: Several dcop algo implementation
Home-page: UNKNOWN
Author: Pierre Rust (Orange)
Author-email: pierre.rust@orange.com
License: UNKNOWN
Keywords: dcop,MAS
Platform: UNKNOWN
Classifier: Development Status :: 4 - Beta
Classifier: Intended Audience :: Developers
Classifier: License :: OSI Approved :: BSD License
Classifier: Operating System :: OS Independent
Classifier: Programming Language :: Python :: 3.5
Classifier: Topic :: Software Development :: Libraries :: Python Modules
Requires-Dist: pulp
Requires-Dist: numpy
Requires-Dist: networkx
Requires-Dist: pyyaml
Requires-Dist: requests
Requires-Dist: websocket-server
Provides-Extra: doc
Requires-Dist: sphinx; extra == 'doc'
Requires-Dist: sphinx-rtd-theme; extra == 'doc'
Provides-Extra: test
Requires-Dist: coverage; extra == 'test'
Requires-Dist: pytest; extra == 'test'
Requires-Dist: mypy; extra == 'test'
